qiskit_validation_addon/__init__.py
qiskit_validation_addon/classifier.py
qiskit_validation_addon/qiskit_interface.py
qiskit_validation_addon-0.0.2.dist-info/METADATA
qiskit_validation_addon-0.0.2.dist-info/WHEEL
qiskit_validation_addon-0.0.2.dist-info/top_level.txt
qiskit_validation_addon-0.0.2.dist-info/RECORD
