Metadata-Version: 2.4
Name: qiskit_validation_addon
Version: 0.0.2
Summary: Classify quantum circuits as Malicious or Benign using a finetuned LLM adapter.
Author: Justin Woodring
Author-email: Justin Woodring <jwoodrg@gmail.com>
License-Expression: MIT
Project-URL: Homepage, https://github.com/JustinWoodring/malicious-qubits
Project-URL: Issues, https://github.com/JustinWoodring/malicious-qubits/issues
Classifier: Programming Language :: Python :: 3
Classifier: Operating System :: OS Independent
Requires-Python: >=3.8
Requires-Dist: torch
Requires-Dist: transformers
Requires-Dist: peft
Requires-Dist: bitsandbytes
Dynamic: author
Dynamic: requires-python
